basicscore/__init__.py
basicscore/cli/__init__.py
basicscore/cli/html/__init__.py
basicscore/cli/html/base.css
basicscore/cli/html/prettify.css
basicscore/cli/html/script.js
basicscore/llm/__init__.py
basicscore/llm/llama.py
basicscore-0.0.3.dist-info/METADATA
basicscore-0.0.3.dist-info/WHEEL
basicscore-0.0.3.dist-info/entry_points.txt
basicscore-0.0.3.dist-info/RECORD
