Metadata-Version: 2.1
Name: basicscore
Version: 0.0.3
Summary: Creates basicness-scores of software
Author-email: Caj Larsson <basic@caj.me>, Billy Bonks <no@example.org>
Requires-Dist: appdirs
Requires-Dist: llama-cpp-python
Requires-Dist: tqdm
Provides-Extra: dev
Requires-Dist: ipython; extra == 'dev'
